monoloco/__init__.py
monoloco/_version.py
monoloco/activity.py
monoloco/predict.py
monoloco/run.py
monoloco/eval/__init__.py
monoloco/eval/eval_activity.py
monoloco/eval/eval_kitti.py
monoloco/eval/eval_variance.py
monoloco/eval/generate_kitti.py
monoloco/eval/geom_baseline.py
monoloco/eval/reid_baseline.py
monoloco/eval/stereo_baselines.py
monoloco/network/__init__.py
monoloco/network/architectures.py
monoloco/network/intrinsics.yaml
monoloco/network/net.py
monoloco/network/process.py
monoloco/prep/__init__.py
monoloco/prep/preprocess_generic.py
monoloco/prep/preprocess_kitti.py
monoloco/prep/preprocess_nu.py
monoloco/prep/transforms.py
monoloco/train/__init__.py
monoloco/train/datasets.py
monoloco/train/hyp_tuning.py
monoloco/train/losses.py
monoloco/train/trainer.py
monoloco/utils/__init__.py
monoloco/utils/camera.py
monoloco/utils/iou.py
monoloco/utils/kitti.py
monoloco/utils/logs.py
monoloco/utils/misc.py
monoloco/utils/nuscenes.py
monoloco/utils/stereo.py
monoloco/visuals/__init__.py
monoloco/visuals/figures.py
monoloco/visuals/orientation.py
monoloco/visuals/pifpaf_show.py
monoloco/visuals/plot_3d_box.py
monoloco/visuals/printer.py
monoloco/visuals/webcam.py
monoloco-0.7.4.6.dist-info/LICENSE
monoloco-0.7.4.6.dist-info/METADATA
monoloco-0.7.4.6.dist-info/WHEEL
monoloco-0.7.4.6.dist-info/top_level.txt
monoloco-0.7.4.6.dist-info/RECORD
