Metadata-Version: 2.1
Name: monoloco
Version: 0.7.4.6
Summary: A 3D vision library from 2D keypoints
Home-page: https://github.com/vita-epfl/monoloco
Author: Lorenzo Bertoni
Author-email: lorenzo.bertoni@epfl.ch
License: GNU AGPLv3
Platform: UNKNOWN
Requires-Dist: pillow (<8.3)
Requires-Dist: openpifpaf (<=v0.12.12,>=v0.12.10)
Requires-Dist: matplotlib
Requires-Dist: pyyaml
Provides-Extra: eval
Requires-Dist: tabulate ; extra == 'eval'
Requires-Dist: sklearn ; extra == 'eval'
Requires-Dist: pandas ; extra == 'eval'
Provides-Extra: prep
Requires-Dist: nuscenes-devkit (==1.0.2) ; extra == 'prep'
Provides-Extra: test
Requires-Dist: pylint ; extra == 'test'
Requires-Dist: pytest ; extra == 'test'
Requires-Dist: gdown ; extra == 'test'
Requires-Dist: scipy ; extra == 'test'
